.DS_Store
empatican/__init__.py
empatican/cli.py
empatican/interface/__init__.py
empatican/interface/connect.py
empatican/physio/__init__.py
empatican/physio/e4.py
test/__init__.py
test/test_connect.py
test/test_e4.py
empatican-0.0.6.dist-info/LICENSE.txt
empatican-0.0.6.dist-info/METADATA
empatican-0.0.6.dist-info/WHEEL
empatican-0.0.6.dist-info/entry_points.txt
empatican-0.0.6.dist-info/top_level.txt
empatican-0.0.6.dist-info/zip-safe
empatican-0.0.6.dist-info/RECORD
