Metadata-Version: 2.1
Name: empatican
Version: 0.0.6
Summary: Empatica Physio Utilities
Home-page: http://github.com/kastman/empatican
Author: Erik Kastman
Author-email: erik.kastman@gmail.com
License: MIT
Platform: UNKNOWN
Classifier: Development Status :: 3 - Alpha
Classifier: License :: OSI Approved :: MIT License
Classifier: Programming Language :: Python
Classifier: Topic :: Utilities
Requires-Dist: pandas
Requires-Dist: requests
Requires-Dist: tqdm
